<?xml version="1.0" encoding="utf-8" ?><dwsync><file name="Attachment.php" server="184.168.138.128//dev/" local="3401451840" remote="11999458052" /><file name="CharsetObserver.php" server="184.168.138.128//dev/" local="3401451840" remote="11999458052" /><file name="ContentEncoder.php" server="184.168.138.128//dev/" local="3401451840" remote="11999458052" /><file name="EmbeddedFile.php" server="184.168.138.128//dev/" local="3401451840" remote="11999458052" /><file name="EncodingObserver.php" server="184.168.138.128//dev/" local="3401451840" remote="11999458052" /><file name="Header.php" server="184.168.138.128//dev/" local="3401451840" remote="11999458052" /><file name="HeaderEncoder.php" server="184.168.138.128//dev/" local="3401451840" remote="11999458052" /><file name="HeaderFactory.php" server="184.168.138.128//dev/" local="3401451840" remote="11999458052" /><file name="HeaderSet.php" server="184.168.138.128//dev/" local="3401451840" remote="11999458052" /><file name="Message.php" server="184.168.138.128//dev/" local="3401451840" remote="11999458052" /><file name="MimeEntity.php" server="184.168.138.128//dev/" local="3401451840" remote="11999458052" /><file name="MimePart.php" server="184.168.138.128//dev/" local="3401451840" remote="11999458052" /><file name="ParameterizedHeader.php" server="184.168.138.128//dev/" local="3401451840" remote="11999458052" /><file name="SimpleHeaderFactory.php" server="184.168.138.128//dev/" local="3401451840" remote="11999458052" /><file name="SimpleHeaderSet.php" server="184.168.138.128//dev/" local="3401451840" remote="11999458052" /><file name="SimpleMessage.php" server="184.168.138.128//dev/" local="3401451840" remote="11999458052" /><file name="SimpleMimeEntity.php" server="184.168.138.128//dev/" local="3401451900" remote="11999458052" /><file name="Attachment.php" server="184.168.138.128" local="3401451840" remote="11999469032" /><file name="CharsetObserver.php" server="184.168.138.128" local="3401451840" remote="11999469032" /><file name="ContentEncoder.php" server="184.168.138.128" local="3401451840" remote="11999469032" /><file name="EmbeddedFile.php" server="184.168.138.128" local="3401451840" remote="11999469032" /><file name="EncodingObserver.php" server="184.168.138.128" local="3401451840" remote="11999469032" /><file name="Header.php" server="184.168.138.128" local="3401451840" remote="11999469032" /><file name="HeaderEncoder.php" server="184.168.138.128" local="3401451840" remote="11999469032" /><file name="HeaderFactory.php" server="184.168.138.128" local="3401451840" remote="11999469032" /><file name="HeaderSet.php" server="184.168.138.128" local="3401451840" remote="11999469032" /><file name="Message.php" server="184.168.138.128" local="3401451840" remote="11999469032" /><file name="MimeEntity.php" server="184.168.138.128" local="3401451840" remote="11999469092" /><file name="MimePart.php" server="184.168.138.128" local="3401451840" remote="11999469092" /><file name="ParameterizedHeader.php" server="184.168.138.128" local="3401451840" remote="11999469092" /><file name="SimpleHeaderFactory.php" server="184.168.138.128" local="3401451840" remote="11999469092" /><file name="SimpleHeaderSet.php" server="184.168.138.128" local="3401451840" remote="11999469092" /><file name="SimpleMessage.php" server="184.168.138.128" local="3401451840" remote="11999469092" /><file name="SimpleMimeEntity.php" server="184.168.138.128" local="3401451900" remote="11999469092" /><file name="Attachment.php" server="www.trueblooddesigns.com/matthewtrueblood/" local="3401451840" remote="12027554792" /><file name="CharsetObserver.php" server="www.trueblooddesigns.com/matthewtrueblood/" local="3401451840" remote="12027554792" /><file name="ContentEncoder.php" server="www.trueblooddesigns.com/matthewtrueblood/" local="3401451840" remote="12027554792" /><file name="EmbeddedFile.php" server="www.trueblooddesigns.com/matthewtrueblood/" local="3401451840" remote="12027554792" /><file name="EncodingObserver.php" server="www.trueblooddesigns.com/matthewtrueblood/" local="3401451840" remote="12027554792" /><file name="Header.php" server="www.trueblooddesigns.com/matthewtrueblood/" local="3401451840" remote="12027554792" /><file name="HeaderEncoder.php" server="www.trueblooddesigns.com/matthewtrueblood/" local="3401451840" remote="12027554792" /><file name="HeaderFactory.php" server="www.trueblooddesigns.com/matthewtrueblood/" local="3401451840" remote="12027554792" /><file name="HeaderSet.php" server="www.trueblooddesigns.com/matthewtrueblood/" local="3401451840" remote="12027554792" /><file name="Message.php" server="www.trueblooddesigns.com/matthewtrueblood/" local="3401451840" remote="12027554792" /><file name="MimeEntity.php" server="www.trueblooddesigns.com/matthewtrueblood/" local="3401451840" remote="12027554792" /><file name="MimePart.php" server="www.trueblooddesigns.com/matthewtrueblood/" local="3401451840" remote="12027554792" /><file name="ParameterizedHeader.php" server="www.trueblooddesigns.com/matthewtrueblood/" local="3401451840" remote="12027554792" /><file name="SimpleHeaderFactory.php" server="www.trueblooddesigns.com/matthewtrueblood/" local="3401451840" remote="12027554792" /><file name="SimpleHeaderSet.php" server="www.trueblooddesigns.com/matthewtrueblood/" local="3401451840" remote="12027554792" /><file name="SimpleMessage.php" server="www.trueblooddesigns.com/matthewtrueblood/" local="3401451840" remote="12027554792" /><file name="SimpleMimeEntity.php" server="www.trueblooddesigns.com/matthewtrueblood/" local="3401451900" remote="12027554792" /></dwsync>